{
    "transparent": "transparent",
    "current": "currentColor",
    "black": "#000000",
    "white": "#FFFFFF",
    "theme": {
        "50": "#f2fdf2",
        "100": "#e5fbe5",
        "200": "#bff6bf",
        "300": "#99f199",
        "400": "#72ec72",
        "500": "#4ce74c",
        "600": "#26e226",
        "700": "#00de00",
        "800": "#00bc00",
        "900": "#009b00"
    },
    "primary": {
        "50": "#fef2f2",
        "100": "#fee5e5",
        "200": "#fcbfbf",
        "300": "#fb9999",
        "400": "#f97272",
        "500": "#f84c4c",
        "600": "#f62626",
        "700": "#f50000",
        "800": "#d00000",
        "900": "#ab0000"
    },
    "secondary": {
        "50": "#fef2f2",
        "100": "#fee5e5",
        "200": "#fcbfbf",
        "300": "#fb9999",
        "400": "#f97272",
        "500": "#f84c4c",
        "600": "#f62626",
        "700": "#f50000",
        "800": "#d00000",
        "900": "#ab0000"
    },
    "background": {
        "light": "transparent",
        "dark": "transparent"
    },
    "gray": {
        "50": "#F4F4F5",
        "100": "#E4E4E7",
        "200": "#D4D4D8",
        "300": "#A1A1AA",
        "400": "#71717A",
        "500": "#52525B",
        "600": "#3F3F46",
        "700": "#27272A",
        "800": "#18181B",
        "900": "#09090B",
        "950": "#09090B"
    },
    "dark": {
        "50": "#F4F4F5",
        "100": "#E4E4E7",
        "200": "#D4D4D8",
        "300": "#A1A1AA",
        "400": "#71717A",
        "500": "#52525B",
        "600": "#3F3F46",
        "700": "#27272A",
        "800": "#18181B",
        "900": "#09090B",
        "950": "#09090B"
    },
    "positive": {
        "50": "#F7FEE7",
        "100": "#ECFCCB",
        "200": "#D9F99D",
        "300": "#BEF264",
        "400": "#A3E635",
        "500": "#84CC16",
        "600": "#65A30D",
        "700": "#4D7C0F",
        "800": "#3F6212",
        "900": "#365314",
        "950": "#1E3A8A"
    },
    "negative": {
        "50": "#FEF2F2",
        "100": "#FEE2E2",
        "200": "#FECACA",
        "300": "#FCA5A5",
        "400": "#F87171",
        "500": "#EF4444",
        "600": "#DC2626",
        "700": "#B91C1C",
        "800": "#991B1B",
        "900": "#7F1D1D",
        "950": "#450A0A"
    },
    "warning": {
        "50": "#FFFBEB",
        "100": "#FEF3C7",
        "200": "#FDE68A",
        "300": "#FCD34D",
        "400": "#FBBF24",
        "500": "#F59E0B",
        "600": "#D97706",
        "700": "#B45309",
        "800": "#92400E",
        "900": "#78350F",
        "950": "#451A03"
    }
}
